yahoo_weather/__init__.py
yahoo_weather/__version__.py
yahoo_weather/api_handler.py
yahoo_weather/weather.py
yahoo_weather/classes/API_param.py
yahoo_weather/classes/__init__.py
yahoo_weather/classes/astronomy.py
yahoo_weather/classes/atmosphere.py
yahoo_weather/classes/condition.py
yahoo_weather/classes/current_observation.py
yahoo_weather/classes/current_weather.py
yahoo_weather/classes/errors.py
yahoo_weather/classes/forecasts.py
yahoo_weather/classes/location.py
yahoo_weather/classes/wind.py
yahoo_weather/config/__init__.py
yahoo_weather/config/config.py
yahoo_weather/config/units.py
yahoo_weather-1.0.7.dist-info/LICENSE
yahoo_weather-1.0.7.dist-info/METADATA
yahoo_weather-1.0.7.dist-info/WHEEL
yahoo_weather-1.0.7.dist-info/top_level.txt
yahoo_weather-1.0.7.dist-info/RECORD
