Metadata-Version: 2.1
Name: yahoo-weather
Version: 1.0.7
Summary: Python library for yahoo weather new API
Home-page: https://github.com/M-Ahadi/yahoo_weather
Author: Mojtaba Ahadi
Author-email: m.ahadi@outlook.com
License: Apache 2.0
Platform: UNKNOWN
Classifier: Programming Language :: Python :: 3
Classifier: License :: OSI Approved :: MIT License
Classifier: Operating System :: OS Independent
Requires-Dist: certifi (==2019.3.9)
Requires-Dist: chardet (==3.0.4)
Requires-Dist: httplib2 (==0.12.1)
Requires-Dist: idna (==2.8)
Requires-Dist: oauth2 (==1.9.0.post1)
Requires-Dist: requests (==2.21.0)
Requires-Dist: urllib3 (==1.24.2)
